chiper_x.py
chiperx/__init__.py
chiperx/aes.py
chiperx/crypt.py
chiperx/rc4.py
chiperx/vichaos.py
chiperx/vichaos_secure.py
chiperx/vigenere.py
chiperx/xor.py
chiper_x-2.1.2.dist-info/METADATA
chiper_x-2.1.2.dist-info/WHEEL
chiper_x-2.1.2.dist-info/entry_points.txt
chiper_x-2.1.2.dist-info/top_level.txt
chiper_x-2.1.2.dist-info/RECORD
