Metadata-Version: 2.4
Name: chiper-x
Version: 2.1.2
Summary: File encryption (with pattern support)
Home-page: https://github.com/DX4GREY/chiper-x
Author: Dx4Grey
Author-email: dxablack@gmail.com
Classifier: Programming Language :: Python :: 3
Classifier: License :: OSI Approved :: MIT License
Classifier: Operating System :: OS Independent
Classifier: Topic :: Security :: Cryptography
Requires-Python: >=3.7
Dynamic: author
Dynamic: author-email
Dynamic: classifier
Dynamic: home-page
Dynamic: requires-python
Dynamic: summary
